{
    "main": {
        "content": "<p>&nbsp; &nbsp;સંવત્‌ ર૦૩૪ના આસો વદિ-૧ર તા.ર૮-૧૦-૧૯૭૮ શનિવારને દિવસ સ્વામી ગામ શ્રી વંથલી મધ્યે વિજય ઈન્ડસ્ટ્રીઝમાં પોતાના ઉતારાની આગળ ઢોલિયા ઉપર સાંજને સમે વિરાજમાન થયા હતા ને સંત હરિભક્તોની સભા ભરાઈને બેઠી હતી.</p><p>&nbsp; &nbsp;પછી સ્વામીએ વાત કરી જે; શાસ્ત્ર માત્ર ધર્મ, અર્થ, કામ પર છે ને જે એને સાંભળે છે ઈ પણ જે કાંઈ <a href=\"dict:સુકૃત\">સુકૃત</a> કરે ઈ ધર્મ, અર્થ, કામ માટે કરે છે. ને એનું ફળ સ્વર્ગ, મૃત્યુ ને પાતાળ છે પણ <a href=\"dict:ગુણાતીત \">ગુણાતીત </a>એવું અક્ષરધામ નથી. ને એક જણો સુકૃત કરે છે ઈ ભગવાનની પ્રસન્નતાને માટે કરે છે ને જે દેખે છે ઈ બુદ્ધિવાળો છે, સર્વ મનુષ્યમાં શ્રેષ્ઠ છે ને સર્વ કર્મનો કરનારો છે તોપણ મોક્ષને યોગ્ય છે. એને સંગે જ <a href=\"dict:નિર્વિકલ્પ\">નિર્વિકલ્પ</a>માં જવાય છે. એમાં આત્મનિષ્ઠ પુરુષ છે. એમાં <a href=\"dict:ષડ્‌ ઉર્મિ\">ષડ્‌ ઉર્મિ</a>એ રહિત પુરુષ છે ને એમાં અક્ષરરૂપે વર્તે એવા પણ છે. ને પુરુષોત્તમ પણ છે. <a href=\"dict:સવિકલ્પ\">સવિકલ્પ</a> નિશ્ચયવાળો છે ઈ ભગવાનમાં દોષ છે પણ કહેતો નથી ને નિર્વિકલ્પવાળો છે એમાં ભક્તમાં પણ દોષ નથી. <a href=\"dict:કનિષ્ઠ\">કનિષ્ઠ</a>માં ને મધ્યમમાં નથી તો ઉત્તમમાં હોય જ કયાંથી ? ભગવાનને આકારે વૃત્તિ હોય ને કાયમ ભગવાનમાં રહેતો હોય એમાં દોષ હોય જ કયાંથી ? જે કોઈ મોટા આવે એની આગળ આની આ વાત કરીએ છીએ. ભગવાનની પ્રસન્નતાને માટે કરે છે. એવો <a href=\"dict:મુમુક્ષુ\">મુમુક્ષુ</a> છે એને જાણે છે ને ઓલ્યો ષટ્‌ કર્મ, ધર્મ, અર્થ ને કામ માટે કરે છે પણ સ્વર્ગ, મૃત્યુ ને પાતાળ એનું ફળ છે. ઓલ્યો ભગવાનના રાજીપા માટે કરે છે એને દેખે છે. એને વિશેષ તો કહેવાય નહીં પણ અવતાર તો કહેવાય જ. એને જાણે છે એટલે ભગવાનની <a href=\"dict:સ્થિતિ\">સ્થિતિ</a> આવી ગઈ. <a href=\"dict:નિર્ગુણ\">નિર્ગુણ</a> વતે નિર્ગુણ થાય પણ આ તો સગુણ છે તોપણ નિર્ગુણમાં મોકલી શકે છે. માટે એને ભગવાન ગણવા હોય તોપણ ગણાય છે. નિર્ગુણમાં એને સર્ટિફિકેટ આપી દ્યે છે. એમ એને સર્વ કર્મનો કરનારો છે. ધર્મ, અર્થ ને કામ પર છે પણ પ્રસન્નતાને અર્થે કરે છે. રાજી થાય એટલા માટે કરે છે. </p>",
        "footer": "।। ઇતિ શ્રી કિરણ પ૯૧ ।।",
        "number": "પ૯૧.",
        "paragraph_count": 2,
        "place": "પીપલાણા",
        "slok_count": 0,
        "title": "નિર્ગુણ થવાનું",
        "word_count": 306
    },
    "meta": {
        "history": "",
        "moral": ""
    }
}