{
    "main": {
        "content": "<p>&nbsp; &nbsp;સંવત્‌ ૨૦૩૧ના વૈશાખ સુદિ-૧૨ તા. ૨૨-૫-૭૫ ગુરુવારને દિવસે શ્રી પીપલાણા મધ્યે પ્રાતઃકાળને સમયે વાત કરી જે; (મધ્યનું૧૬) એક ધર્મનિષ્ઠા ને બીજી <a href=\"dict:સ્વરૂપનિષ્ઠા\">સ્વરૂપનિષ્ઠા</a>; ધર્મનિષ્ઠા રાખે તો સ્વરૂપનિષ્ઠા મોળી પડી જાય ને સ્વરૂપનિષ્ઠા રાખે તો ધર્મનિષ્ઠા મોળી પડી જાય. માટે કોને રાખવી અને કોને ત્યાગ કરવી ? ધર્મ પાળવો તે ધર્મનિષ્ઠા અને ધર્મ પાળનારનો સંબંધ રાખવો તે સ્વરૂપનિષ્ઠા. સ્વરૂપનિષ્ઠા વરને ઠેકાણે છે ને બીજાં સાધન તો જાનૈયાને ઠેકાણે છે (ગુ. સ્વામીની વાતો). </p>",
        "footer": "।। ઇતિ શ્રી કિરણ ૩ ।।",
        "number": "૩.",
        "paragraph_count": 1,
        "place": "પીપલાણા",
        "slok_count": 0,
        "title": "ધર્મનિષ્ઠાનું તથા સ્વરૂપનિષ્ઠાનું",
        "word_count": 83
    },
    "meta": {
        "history": "",
        "moral": "",
        "date": "સંવત્‌ ૨૦૩૧ વૈશાખ સુદિ-૧૨, તા. ૨૨-૫-૭૫ ગુરુવાર, પ્રાતઃકાળ",
        "summary": [
            "બે પ્રકારની નિષ્ઠા: ધર્મનિષ્ઠા અને સ્વરૂપનિષ્ઠા - એક રાખે તો બીજી મોળી પડે.",
            "ધર્મનિષ્ઠા એટલે ધર્મ પાળવો; સ્વરૂપનિષ્ઠા એટલે ધર્મ પાળનારનો સંબંધ રાખવો.",
            "સ્વરૂપનિષ્ઠા વરને (શ્રેષ્ઠને) ઠેકાણે છે અને બીજાં સાધનો તો જાણનારાને ઠેકાણે છે."
        ]
    }
}